{"@context":"https://schema.org","@type":"Service","serviceType":"Monopoly GO Sticker Service","provider":{"@type":"Organization","name":"babixGO","url":"https://babixgo.de"},"name":"Monopoly GO Sticker","description":"Fehlende Monopoly GO Sticker schnell und zuverlässig erhalten. Direkter Service per WhatsApp.","url":"https://babixgo.de/sticker/","areaServed":"DE","availableChannel":{"@type":"ServiceChannel","serviceUrl":"https://wa.me/4915223842897","servicePhone":"+49-152-23842897","availableLanguage":"de"},"category":"Gaming Service","offers":{"@type":"Offer","availability":"https://schema.org/InStock","priceSpecification":{"@type":"PriceSpecification","priceCurrency":"EUR"}}}
